Metadata-Version: 2.1
Name: lsp-python
Version: 0.0.3.post1
Summary: lsp-python is a lightweight implementation of the Least Square Projection (LSP) dimensionality reduction technique using a sklearn style API.
Home-page: https://github.com/lvcarx/pyLSP
Author: Luca Reichmann
Author-email: st169765@stud.uni-stuttgart.de
License: MIT
Classifier: Programming Language :: Python :: 3.11
License-File: LICENSE
Requires-Dist: numpy
Requires-Dist: scikit-learn
Requires-Dist: matplotlib
